weather.py
iflow_mcp_sidharthrajaram_mcp_sse-0.1.1.dist-info/METADATA
iflow_mcp_sidharthrajaram_mcp_sse-0.1.1.dist-info/WHEEL
iflow_mcp_sidharthrajaram_mcp_sse-0.1.1.dist-info/entry_points.txt
iflow_mcp_sidharthrajaram_mcp_sse-0.1.1.dist-info/RECORD
