Metadata-Version: 2.4
Name: iflow-mcp-sidharthrajaram-mcp-sse
Version: 0.1.1
Summary: SSE-based MCP Server and Client
Requires-Python: >=3.11
Requires-Dist: anthropic>=0.45.1
Requires-Dist: argparse>=1.4.0
Requires-Dist: httpx>=0.28.1
Requires-Dist: mcp[cli]>=1.2.1
Requires-Dist: python-dotenv>=1.0.1
